NlvLog.cp37-win_amd64.pyd
boost_python37-vc140-mt-gd-x64-1_72.dll
boost_python37-vc140-mt-x64-1_72.dll
tbb.dll
NlvCore/Channel.py
NlvCore/Chart.py
NlvCore/DataExplorer.py
NlvCore/Document.py
NlvCore/EventDisplay.py
NlvCore/EventProjector.py
NlvCore/EventView.py
NlvCore/Extension.py
NlvCore/Global.py
NlvCore/Launch.py
NlvCore/Logfile.py
NlvCore/Logmeta.py
NlvCore/Main.py
NlvCore/MatchNode.py
NlvCore/Project.py
NlvCore/PythonEditor.py
NlvCore/Session.py
NlvCore/Shell.py
NlvCore/StyleNode.py
NlvCore/TangledTree.py
NlvCore/Theme.py
NlvCore/Version.py
NlvCore/View.py
NlvCore/__init__.py
NlvCore/_defaults.xml
NlvCore/_field_names.xml
NlvCore/theme.event.default.xml
NlvCore/theme.global.default.xml
NlvCore/theme.log.default.xml
NlvCore/theme.view.default.xml
NlvCore/Ico/if_gear_blue_10437.ico
NlvCore/Ico/if_gear_green_10438.ico
NlvCore/Ico/if_gear_red_10439.ico
NlvCore/Ico/if_gear_yellow_10440.ico
NlvCore/Ico/if_puzzle_blue_10502.ico
NlvCore/Ico/if_puzzle_green_10503.ico
NlvCore/Ico/if_puzzle_red_10504.ico
NlvCore/Ico/if_puzzle_yellow_10505.ico
NlvCore/Sphinx/doctrees/building.doctree
NlvCore/Sphinx/doctrees/environment.pickle
NlvCore/Sphinx/doctrees/events.doctree
NlvCore/Sphinx/doctrees/index.doctree
NlvCore/Sphinx/doctrees/issues.doctree
NlvCore/Sphinx/doctrees/keyboard.doctree
NlvCore/Sphinx/doctrees/licenses.doctree
NlvCore/Sphinx/doctrees/logfile.doctree
NlvCore/Sphinx/doctrees/overview.doctree
NlvCore/Sphinx/doctrees/references.doctree
NlvCore/Sphinx/doctrees/schema.doctree
NlvCore/Sphinx/doctrees/searching.doctree
NlvCore/Sphinx/doctrees/session.doctree
NlvCore/Sphinx/doctrees/views.doctree
NlvCore/Sphinx/doctrees/vsnlv.doctree
NlvCore/Sphinx/html/building.html
NlvCore/Sphinx/html/events.html
NlvCore/Sphinx/html/genindex.html
NlvCore/Sphinx/html/index.html
NlvCore/Sphinx/html/issues.html
NlvCore/Sphinx/html/keyboard.html
NlvCore/Sphinx/html/licenses.html
NlvCore/Sphinx/html/logfile.html
NlvCore/Sphinx/html/objects.inv
NlvCore/Sphinx/html/overview.html
NlvCore-531.0.dist-info/METADATA
NlvCore-531.0.dist-info/WHEEL
NlvCore-531.0.dist-info/entry_points.txt
NlvCore-531.0.dist-info/top_level.txt
NlvCore-531.0.dist-info/RECORD
